PyCloudFS/__init__.py
PyCloudFS/amazon_web_service.py
PyCloudFS/base_abstract.py
PyCloudFS/base_exceptions.py
PyCloudFS/google_cloud_storage.py
pycloudfs-0.0.2.dist-info/LICENSE
pycloudfs-0.0.2.dist-info/METADATA
pycloudfs-0.0.2.dist-info/WHEEL
pycloudfs-0.0.2.dist-info/top_level.txt
pycloudfs-0.0.2.dist-info/RECORD
